Workbook

Sheet Reporting Template
B2: ILPA Reporting Template (v. 1.1) - This packet was last updated on Oct. 17, 2016 | O2: Inception Start: | P2: 42185
B3: The Veritas Capital Fund V, LP | E3: QTD | F3: YTD | G3: Since Inception | H3: QTD | I3: YTD | J3: Since Inception | K3: QTD | L3: YTD | M3: Since Inception | O3: Current Year Start: | P3: 44562
E4: =P4 -> 44652 | F4: =P3 -> 44562 | G4: =P2 -> 42185 | H4: =P4 -> 44652 | I4: =P3 -> 44562 | J4: =P2 -> 42185 | K4: =P4 -> 44652 | L4: =P3 -> 44562 | M4: =P2 -> 42185 | O4: Current Period Start: | P4: 44652
E5: =$P$5 -> 44742 | F5: =$P$5 -> 44742 | G5: =$P$5 -> 44742 | H5: =$P$5 -> 44742 | I5: =$P$5 -> 44742 | J5: =$P$5 -> 44742 | K5: =$P$5 -> 44742 | L5: =$P$5 -> 44742 | M5: =$P$5 -> 44742 | O5: Period End: | P5: 44742
B7: A. Capital Account Statement for Investor Name
B8: A.1 NAV Reconciliation and Summary of Fees, Expenses & Incentive Allocation | E8: Investor's Allocation of Total Fund | H8: Total Fund (incl. GP Allocation) | K8: GP's Allocation of Total Fund
B9: Beginning NAV - Net of Incentive Allocation | E9: 0 | F9: 0 | G9: 0 | H9: 0 | I9: 0 | J9: 0 | K9: 0 | L9: 0 | M9: 0
B10: Contributions - Cash & Non-Cash | E10: 0 | F10: 0 | G10: 0 | H10: 0 | I10: 0 | J10: 0 | K10: 0 | L10: 0 | M10: 0
B11: Distributions - Cash & Non-Cash (input positive values) | E11: 0 | F11: 0 | G11: 0 | H11: 0 | I11: 0 | J11: 0 | K11: 0 | L11: 0 | M11: 0
B12: Total Cash / Non-Cash Flows (contributions, less distributions) | E12: =E10-E11 -> 0 | F12: =F10-F11 -> 0 | G12: =G10-G11 -> 0 | H12: =H10-H11 -> 0 | I12: =I10-I11 -> 0 | J12: =J10-J11 -> 0 | K12: =K10-K11 -> 0 | L12: =L10-L11 -> 0 | M12: =M10-M11 -> 0
B13: Net Operating Income (Expense):
B14: (Management Fees – Gross of Offsets, Waivers & Rebates): | E14: 0 | F14: 0 | G14: 0 | H14: 0 | I14: 0 | J14: 0 | K14: 0 | L14: 0 | M14: 0
B15: Management Fee Rebate | E15: 0 | F15: 0 | G15: 0 | H15: 0 | I15: 0 | J15: 0 | K15: 0 | L15: 0 | M15: 0
B16: (Partnership Expenses - Total): | E16: =SUM(E17:E25) -> 0 | F16: =SUM(F17:F25) -> 0 | G16: =SUM(G17:G25) -> 0 | H16: =SUM(H17:H25) -> 0 | I16: =SUM(I17:I25) -> 0 | J16: =SUM(J17:J25) -> 0 | K16: =SUM(K17:K25) -> 0 | L16: =SUM(L17:L25) -> 0 | M16: =SUM(M17:M25) -> 0
B17: (Partnership Expenses – Accounting, Administration & IT) | E17: 0 | F17: 0 | G17: 0 | H17: 0 | I17: 0 | J17: 0 | K17: 0 | L17: 0 | M17: 0
B18: (Partnership Expenses – Audit & Tax Preparatory) | E18: 0 | F18: 0 | G18: 0 | H18: 0 | I18: 0 | J18: 0 | K18: 0 | L18: 0 | M18: 0
B19: (Partnership Expenses – Bank Fees) | E19: 0 | F19: 0 | G19: 0 | H19: 0 | I19: 0 | J19: 0 | K19: 0 | L19: 0 | M19: 0
B20: (Partnership Expenses – Custody Fees) | E20: 0 | F20: 0 | G20: 0 | H20: 0 | I20: 0 | J20: 0 | K20: 0 | L20: 0 | M20: 0
B21: (Partnership Expenses – Due Diligence) | E21: 0 | F21: 0 | G21: 0 | H21: 0 | I21: 0 | J21: 0 | K21: 0 | L21: 0 | M21: 0
B22: (Partnership Expenses – Legal) | E22: 0 | F22: 0 | G22: 0 | H22: 0 | I22: 0 | J22: 0 | K22: 0 | L22: 0 | M22: 0
B23: (Partnership Expenses – Organization Costs) | E23: 0 | F23: 0 | G23: 0 | H23: 0 | I23: 0 | J23: 0 | K23: 0 | L23: 0 | M23: 0
B24: (Partnership Expenses – Other Travel & Entertainment) | E24: 0 | F24: 0 | G24: 0 | H24: 0 | I24: 0 | J24: 0 | K24: 0 | L24: 0 | M24: 0
B25: (Partnership Expenses – Other+) | E25: 0 | F25: 0 | G25: 0 | H25: 0 | I25: 0 | J25: 0 | K25: 0 | L25: 0 | M25: 0
B26: Total Offsets to Fees & Expenses (applied during period): | E26: 0 | F26: 0 | G26: 0 | H26: 0 | I26: 0 | J26: 0 | K26: 0 | L26: 0 | M26: 0
B27: Offset Categories | D27: % Offset to Investor
B28: Advisory Fee Offset | D28: 0 | E28: 0 | F28: 0 | G28: 0 | H28: 0 | I28: 0 | J28: 0 | K28: 0 | L28: 0 | M28: 0
B29: Broken Deal Fee Offset | D29: 0 | E29: 0 | F29: 0 | G29: 0 | H29: 0 | I29: 0 | J29: 0 | K29: 0 | L29: 0 | M29: 0
B30: Transaction & Deal Fee Offset | D30: 0 | E30: 0 | F30: 0 | G30: 0 | H30: 0 | I30: 0 | J30: 0 | K30: 0 | L30: 0 | M30: 0
B31: Directors Fee Offset | D31: 0 | E31: 0 | F31: 0 | G31: 0 | H31: 0 | I31: 0 | J31: 0 | K31: 0 | L31: 0 | M31: 0
B32: Monitoring Fee Offset | D32: 0 | E32: 0 | F32: 0 | G32: 0 | H32: 0 | I32: 0 | J32: 0 | K32: 0 | L32: 0 | M32: 0
B33: Capital Markets Fee Offset | D33: 0 | E33: 0 | F33: 0 | G33: 0 | H33: 0 | I33: 0 | J33: 0 | K33: 0 | L33: 0 | M33: 0
B34: Organization Cost Offset | D34: 0 | E34: 0 | F34: 0 | G34: 0 | H34: 0 | I34: 0 | J34: 0 | K34: 0 | L34: 0 | M34: 0
B35: Placement Fee Offset | D35: 0 | E35: 0 | F35: 0 | G35: 0 | H35: 0 | I35: 0 | J35: 0 | K35: 0 | L35: 0 | M35: 0
B36: Other Offset+ | D36: 0 | E36: 0 | F36: 0 | G36: 0 | H36: 0 | I36: 0 | J36: 0 | K36: 0 | L36: 0 | M36: 0
B37: Reconciliation for Unapplied Offset Balance (Roll-forward) | C37: Unapplied Offset Balance (Roll-forward) - Beginning Balance | E37: 0 | F37: 0 | G37: 0 | H37: 0 | I37: 0 | J37: 0 | K37: 0 | L37: 0 | M37: 0
C38: Plus: Total Offsets to Fees & Expenses (recognized during period) | E38: =SUM(E28:E36) -> 0 | F38: =SUM(F28:F36) -> 0 | G38: =SUM(G28:G36) -> 0 | H38: =SUM(H28:H36) -> 0 | I38: =SUM(I28:I36) -> 0 | J38: =SUM(J28:J36) -> 0 | K38: =SUM(K28:K36) -> 0 | L38: =SUM(L28:L36) -> 0 | M38: =SUM(M28:M36) -> 0
C39: Less: Total Offsets to Fees & Expenses (applied during period) | E39: =E26 -> 0 | F39: =F26 -> 0 | G39: =G26 -> 0 | H39: =H26 -> 0 | I39: =I26 -> 0 | J39: =J26 -> 0 | K39: =K26 -> 0 | L39: =L26 -> 0 | M39: =M26 -> 0
C40: Unapplied Offset Balance (Roll-forward) - Ending Balance | E40: =E37+E38-E39 -> 0 | F40: =F37+F38-F39 -> 0 | G40: =G37+G38-G39 -> 0 | H40: =H37+H38-H39 -> 0 | I40: =I37+I38-I39 -> 0 | J40: =J37+J38-J39 -> 0 | K40: =K37+K38-K39 -> 0 | L40: =L37+L38-L39 -> 0 | M40: =M37+M38-M39 -> 0
B41: (Total Management Fees & Partnership Expenses, Net of Offsets & Rebates, Gross of Fee Waiver) | E41: =E14+E15+E16+E26 -> 0 | F41: =F14+F15+F16+F26 -> 0 | G41: =G14+G15+G16+G26 -> 0 | H41: =H14+H15+H16+H26 -> 0 | I41: =I14+I15+I16+I26 -> 0 | J41: =J14+J15+J16+J26 -> 0 | K41: =K14+K15+K16+K26 -> 0 | L41: =L14+L15+L16+L26 -> 0 | M41: =M14+M15+M16+M26 -> 0
B42: Fee Waiver | E42: 0 | F42: 0 | G42: 0 | H42: 0 | I42: 0 | J42: 0 | K42: 0 | L42: 0 | M42: 0
B43: Interest Income | E43: 0 | F43: 0 | G43: 0 | H43: 0 | I43: 0 | J43: 0 | K43: 0 | L43: 0 | M43: 0
B44: Dividend Income | E44: 0 | F44: 0 | G44: 0 | H44: 0 | I44: 0 | J44: 0 | K44: 0 | L44: 0 | M44: 0
B45: (Interest Expense) | E45: 0 | F45: 0 | G45: 0 | H45: 0 | I45: 0 | J45: 0 | K45: 0 | L45: 0 | M45: 0
B46: Other Income/(Expense)+ | E46: 0 | F46: 0 | G46: 0 | H46: 0 | I46: 0 | J46: 0 | K46: 0 | L46: 0 | M46: 0
B47: Total Net Operating Income / (Expense) | E47: =SUM(E41:E46) -> 0 | F47: =SUM(F41:F46) -> 0 | G47: =SUM(G41:G46) -> 0 | H47: =SUM(H41:H46) -> 0 | I47: =SUM(I41:I46) -> 0 | J47: =SUM(J41:J46) -> 0 | K47: =SUM(K41:K46) -> 0 | L47: =SUM(L41:L46) -> 0 | M47: =SUM(M41:M46) -> 0
B48: (Placement Fees) | E48: 0 | F48: 0 | G48: 0 | H48: 0 | I48: 0 | J48: 0 | K48: 0 | L48: 0 | M48: 0
B49: Realized Gain / (Loss) | E49: 0 | F49: 0 | G49: 0 | H49: 0 | I49: 0 | J49: 0 | K49: 0 | L49: 0 | M49: 0
B50: Change in Unrealized Gain / (Loss) | E50: 0 | F50: 0 | G50: 0 | H50: 0 | I50: 0 | J50: 0 | K50: 0 | L50: 0 | M50: 0
B51: Ending NAV - Net of Incentive Allocation | E51: =E9+E12+E47+E48+E49+E50 -> 0 | F51: =F9+F12+F47+F48+F49+F50 -> 0 | G51: =G9+G12+G47+G48+G49+G50 -> 0 | H51: =H9+H12+H47+H48+H49+H50 -> 0 | I51: =I9+I12+I47+I48+I49+I50 -> 0 | J51: =J9+J12+J47+J48+J49+J50 -> 0 | K51: =K9+K12+K47+K48+K49+K50 -> 0 | L51: =L9+L12+L47+L48+L49+L50 -> 0 | M51: =M9+M12+M47+M48+M49+M50 -> 0
B52: Reconciliation for Accrued Incentive Allocation | C52: Accrued Incentive Allocation - Starting Period Balance | E52: 0 | F52: 0 | G52: 0 | H52: 0 | I52: 0 | J52: 0 | K52: 0 | L52: 0 | M52: 0
C53: Incentive Allocation - Paid During the Period | E53: 0 | F53: 0 | G53: 0 | H53: 0 | I53: 0 | J53: 0 | K53: 0 | L53: 0 | M53: 0
C54: Accrued Incentive Allocation - Periodic Change | E54: 0 | F54: 0 | G54: 0 | H54: 0 | I54: 0 | J54: 0 | K54: 0 | L54: 0 | M54: 0
C55: Accrued Incentive Allocation - Ending Period Balance | E55: =SUM(E52:E54) -> 0 | F55: =SUM(F52:F54) -> 0 | G55: =SUM(G52:G54) -> 0 | H55: =SUM(H52:H54) -> 0 | I55: =SUM(I52:I54) -> 0 | J55: =SUM(J52:J54) -> 0 | K55: =SUM(K52:K54) -> 0 | L55: =SUM(L52:L54) -> 0 | M55: =SUM(M52:M54) -> 0
C56: Ending NAV - Gross of Accrued Incentive Allocation | E56: =E51-E55 -> 0 | F56: =F51-F55 -> 0 | G56: =G51-G55 -> 0 | H56: =H51-H55 -> 0 | I56: =I51-I55 -> 0 | J56: =J51-J55 -> 0 | K56: =K51-K55 -> 0 | L56: =L51-L55 -> 0 | M56: =M51-M55 -> 0
B58: A.2 Commitment Reconciliation: | E58: Investor's Allocation of Total Fund | H58: =H8 -> Total Fund (incl. GP Allocation) | K58: =K8 -> GP's Allocation of Total Fund
B59: Total Commitment | E59: 0 | F59: =E59 -> 0 | G59: =E59 -> 0 | H59: 0 | I59: =H59 -> 0 | J59: =H59 -> 0 | K59: 0 | L59: =K59 -> 0 | M59: =K59 -> 0
B60: Beginning Unfunded Commitment: | E60: 0 | F60: 0 | G60: =E59 -> 0 | H60: 0 | I60: 0 | J60: =H59 -> 0 | K60: 0 | L60: 0 | M60: =K59 -> 0
B61: (Less Contributions) | E61: 0 | F61: 0 | G61: 0 | H61: 0 | I61: 0 | J61: 0 | K61: 0 | L61: 0 | M61: 0
B62: Plus Recallable Distributions | E62: 0 | F62: 0 | G62: 0 | H62: 0 | I62: 0 | J62: 0 | K62: 0 | L62: 0 | M62: 0
B63: (Less Expired/Released Commitments) | E63: 0 | F63: 0 | G63: 0 | H63: 0 | I63: 0 | J63: 0 | K63: 0 | L63: 0 | M63: 0
B64: +/- Other Unfunded Adjustment | E64: 0 | F64: 0 | G64: 0 | H64: 0 | I64: 0 | J64: 0 | K64: 0 | L64: 0 | M64: 0
B65: Ending Unfunded Commitment | E65: =SUM(E60:E64) -> 0 | F65: =SUM(F60:F64) -> 0 | G65: =SUM(G60:G64) -> 0 | H65: =SUM(H60:H64) -> 0 | I65: =SUM(I60:I64) -> 0 | J65: =SUM(J60:J64) -> 0 | K65: =SUM(K60:K64) -> 0 | L65: =SUM(L60:L64) -> 0 | M65: =SUM(M60:M64) -> 0
B67: A.3 Miscellaneous** (input positive values): | E67: Investor's Allocation of Total Fund | H67: =H8 -> Total Fund (incl. GP Allocation) | K67: =K8 -> GP's Allocation of Total Fund
B68: Incentive Allocation - Earned (period-end balance)**** | E68: 0 | F68: =E68 -> 0 | G68: =E68 -> 0 | H68: 0 | I68: =H68 -> 0 | J68: =H68 -> 0 | K68: 0 | L68: =K68 -> 0 | M68: =K68 -> 0
B69: Incentive Allocation - Amount Held in Escrow (period-end balance)**** | E69: 0 | F69: =E69 -> 0 | G69: =E69 -> 0 | H69: 0 | I69: =H69 -> 0 | J69: 0 | K69: 0 | L69: =K69 -> 0 | M69: =K69 -> 0
B70: Returned Clawback**** | E70: 0 | F70: 0 | G70: 0 | H70: 0 | I70: 0 | J70: 0 | K70: 0 | L70: 0 | M70: 0
B71: Capitalized Transaction Fees & Exp. - Paid to Non-Related Parties**** | E71: 0 | F71: 0 | G71: 0 | H71: 0 | I71: 0 | J71: 0
B72: Distributions Relating to Fees & Expenses**** | E72: 0 | F72: 0 | G72: 0 | H72: 0 | I72: 0 | J72: 0
B73: Fund of Funds: Gross Fees, Exp. & Incentive Allocation paid to the Underlying Funds**** | E73: =IFERROR(H73*E59/H59,0) -> 0 | F73: =IFERROR(I73*E59/H59,0) -> 0 | G73: =IFERROR(J73*E59/H59,0) -> 0 | H73: 0 | I73: 0 | J73: 0
B74: B. Schedule of Fees, Incentive Allocation & Reimbursements Received by the GP & Related Parties, with Respect to the Fund and Portfolio Companies/Investments Held by the Fund
B76: B.1 Source Allocation: | E76: Investor's Allocation of Total Fund | H76: Cumulative LPs' Allocation of Total Fund | K76: Affiliated Positions***
B77: With Respect to the Fund's LPs | C77: Management Fees - Net of Rebates, Gross of Offsets and Waivers | E77: =-(E14+E15) -> 0 | F77: =-(F14+F15) -> 0 | G77: =-(G14+G15) -> 0 | H77: =-(H14+H15-K14-K15) -> 0 | I77: =-(I14+I15-L14-L15) -> 0 | J77: =-(J14+J15-M14-M15) -> 0
C78: Partnership Expenses - Paid to GP & Related Parties - Gross of Offsets | E78: 0 | F78: 0 | G78: 0 | H78: 0 | I78: 0 | J78: 0
C79: (Less Total Offsets to Fees & Expenses - applied during period) | E79: =-E26 -> 0 | F79: =-F26 -> 0 | G79: =-G26 -> 0 | H79: =-H26 -> 0 | I79: =-I26 -> 0 | J79: =-J26 -> 0
C80: Capitalized Transaction Fees & Exp. - Paid to GP & Related Parties**** | E80: 0 | F80: 0 | G80: 0 | H80: 0 | I80: 0 | J80: 0
C81: Accrued Incentive Allocation - Periodic Change | E81: =-E54 -> 0 | F81: =-F54 -> 0 | G81: =-G54 -> 0 | H81: =K54 -> 0 | I81: =L54 -> 0 | J81: =M54 -> 0
B82: With Respect to the Fund's Portfolio Companies/ Invs. | C82: Total Fees with Respect to Portfolio Companies/Investments: | E82: =SUM(E83:E89) -> 0 | F82: =SUM(F83:F89) -> 0 | G82: =SUM(G83:G89) -> 0 | H82: =SUM(H83:H89) -> 0 | I82: =SUM(I83:I89) -> 0 | J82: =SUM(J83:J89) -> 0 | K82: =SUM(K83:K89) -> 0 | L82: =SUM(L83:L89) -> 0 | M82: =SUM(M83:M89) -> 0
C83: Advisory Fees**** | E83: 0 | F83: 0 | G83: 0 | H83: 0 | I83: 0 | J83: 0 | K83: 0 | L83: 0 | M83: 0
C84: Broken Deal Fees**** | E84: 0 | F84: 0 | G84: 0 | H84: 0 | I84: 0 | J84: 0 | K84: 0 | L84: 0 | M84: 0
C85: Transaction & Deal Fees**** | E85: 0 | F85: 0 | G85: 0 | H85: 0 | I85: 0 | J85: 0 | K85: 0 | L85: 0 | M85: 0
C86: Directors Fees**** | E86: 0 | F86: 0 | G86: 0 | H86: 0 | I86: 0 | J86: 0 | K86: 0 | L86: 0 | M86: 0
C87: Monitoring Fees**** | E87: 0 | F87: 0 | G87: 0 | H87: 0 | I87: 0 | J87: 0 | K87: 0 | L87: 0 | M87: 0
C88: Capital Markets Fees**** | E88: 0 | F88: 0 | G88: 0 | H88: 0 | I88: 0 | J88: 0 | K88: 0 | L88: 0 | M88: 0
C89: Other Fees****, + | E89: 0 | F89: 0 | G89: 0 | H89: 0 | I89: 0 | J89: 0 | K89: 0 | L89: 0 | M89: 0
C90: Total Reimbursements for Travel & Administrative Expenses**** | E90: 0 | F90: 0 | G90: 0 | H90: 0 | I90: 0 | J90: 0 | K90: 0 | L90: 0 | M90: 0
B91: Total Received by the GP & Related Parties | E91: =SUM(E77:E82,E90) -> 0 | F91: =SUM(F77:F82,F90) -> 0 | G91: =SUM(G77:G82,G90) -> 0 | H91: =SUM(H77:H82,H90) -> 0 | I91: =SUM(I77:I82,I90) -> 0 | J91: =SUM(J77:J82,J90) -> 0 | K91: =SUM(K77:K82,K90) -> 0 | L91: =SUM(L77:L82,L90) -> 0 | M91: =SUM(M77:M82,M90) -> 0
B93: *Current offset percentages for the specific LP; As offset calculations may change over the life of the Fund, the current offset percentages may not be applicable for calculating the non-QTD offset balances
B94: **Content in A.3 aims to provide users with additional context on the balances provided in other sections; Some of the balances in A.3 represent a sub-total for an amount provided in another section; Balances in this section should be entered as a positive amount, even though similar balances in other sections may typically be presented as a negative amount; To prevent double-counting, or other miscalculations, users should avoid netting balances in A.3 with amounts in other sections
B95: ***Balances in this section represent fees & reimbursements received by the GP/Manager/Related Parties with respect to the Fund's investments that are not allocable to the Total Fund (i.e. allocated to ownership interests of LP co-investors & other vehicles managed-by/affiliated-with the GP/Manager/Related Party); To avoid double-counting, LP # 5's Allocation of Total Fund should not reflect any pro-rata share of these positions; Balances in this section, plus the balances in the "Cumulative LPs' Allocation of Total Fund" section, should equal the total fees/reimbursements received by the GP/Manager/Related Parties With Respect to the Fund's Portfolio Companies/Invs.
B96: ****Allocation for individual LPs, the Total Fund and all remaining positions may need to be estimated on a pro-rata basis
B97: +A description should be provided in the footnote section for any amount(s) listed in this row for the year-to-date period
B99: Shaded/Italicized/Grouped Content Represents Level 2 Data
B101: Footnotes for any YTD (Total Fund) expenses, fees & offsets (including any "other" balances)

Sheet Cross-Check
B1: ILPA LP Section — Cross-Check & Reconciliation
B2: Enter PDF values in the orange column. Green = match · Red = discrepancy. Fix discrepancies in Reporting Template before delivering.
B4: Check Item | C4: PDF Value (enter here) | D4: Template Computed (auto-formula) | E4: Difference | F4: Status | G4: Notes / What to check if it fails
B5: A.1 NAV Reconciliation
B6: Ending NAV — Net (QTD) | D6: ='Reporting Template'!E51 -> 0 | E6: =IF(C6="","",C6-D6) | F6: =IF(C6="","—",IF(ABS(C6-D6)<1,"✓ OK","✗ FAIL")) -> — | G6: Check all 6 inputs to E51: rows 9,10,11,47,48,49,50
B7: Ending NAV — Net (YTD) | D7: ='Reporting Template'!F51 -> 0 | E7: =IF(C7="","",C7-D7) | F7: =IF(C7="","—",IF(ABS(C7-D7)<1,"✓ OK","✗ FAIL")) -> — | G7: YTD: verify F9 = Q1 beginning NAV; check F10,F50
B8: Ending NAV — Net (SI) | D8: ='Reporting Template'!G51 -> 0 | E8: =IF(C8="","",C8-D8) | F8: =IF(C8="","—",IF(ABS(C8-D8)<1,"✓ OK","✗ FAIL")) -> — | G8: SI: verify G9=0, G10=cumulative contributions, G50=SI unrealised
B9: Ending NAV — Gross (QTD) | D9: ='Reporting Template'!E56 -> 0 | E9: =IF(C9="","",C9-D9) | F9: =IF(C9="","—",IF(ABS(C9-D9)<1,"✓ OK","✗ FAIL")) -> — | G9: Gross = Net − Carry End. Check E55 (carry) if wrong
B10: Carry Ending Balance (QTD) | D10: ='Reporting Template'!E55 -> 0 | E10: =IF(C10="","",C10-D10) | F10: =IF(C10="","—",IF(ABS(C10-D10)<1,"✓ OK","✗ FAIL")) -> — | G10: Carry end = start + paid + periodic change (rows 52+53+54)
B11: Total Net Op Income (QTD) | D11: ='Reporting Template'!E47 -> 0 | E11: =IF(C11="","",C11-D11) | F11: =IF(C11="","—",IF(ABS(C11-D11)<1,"✓ OK","✗ FAIL")) -> — | G11: Check rows 41-46. Most common: wrong sign on interest expense
B12: Net Mgmt Fees & Exp (QTD) | D12: ='Reporting Template'!E41 -> 0 | E12: =IF(C12="","",C12-D12) | F12: =IF(C12="","—",IF(ABS(C12-D12)<1,"✓ OK","✗ FAIL")) -> — | G12: E14+E15+E16+E26. If wrong: check row 16 sub-rows vs row 26
B13: Partnership Exp Total (QTD) | D13: ='Reporting Template'!E16 -> 0 | E13: =IF(C13="","",C13-D13) | F13: =IF(C13="","—",IF(ABS(C13-D13)<1,"✓ OK","✗ FAIL")) -> — | G13: SUM(E17:E25). Enter expenses in sub-rows only, never in E16
B15: Offset Roll-Forward — Double-Count Check
B16: Offsets Applied (QTD) = Offset sub-cats | D16: ='Reporting Template'!E38 -> 0 | E16: =IF(C16="","",C16-D16) | F16: =IF(C16="","—",IF(ABS(C16-D16)<1,"✓ OK","✗ FAIL")) -> — | G16: E38=SUM(E28:E36). Must equal E26 when unapplied balance is zero
B17: Unapplied Offset Ending (QTD) | D17: ='Reporting Template'!E40 -> 0 | E17: =IF(C17="","",C17-D17) | F17: =IF(C17="","—",IF(ABS(C17-D17)<1,"✓ OK","✗ FAIL")) -> — | G17: E37+E38-E39. Should match PDF unapplied balance. Common error: using + instead of -
B18: Offset % check — Monitoring | D18: ='Reporting Template'!E32 -> 0 | E18: =IF(C18="","",C18-D18) | F18: =IF(C18="","—",IF(ABS(C18-D18)<1,"✓ OK","✗ FAIL")) -> — | G18: Enter monitoring fee credits. Should sum with other sub-cats to match E26
B19: Offset % check — Transaction | D19: ='Reporting Template'!E30 -> 0 | E19: =IF(C19="","",C19-D19) | F19: =IF(C19="","—",IF(ABS(C19-D19)<1,"✓ OK","✗ FAIL")) -> — | G19: Enter transaction fee credits. Often appears in SI column only
B21: A.2 Commitment Reconciliation
B22: Ending Unfunded (QTD) | D22: ='Reporting Template'!E65 -> 0 | E22: =IF(C22="","",C22-D22) | F22: =IF(C22="","—",IF(ABS(C22-D22)<1,"✓ OK","✗ FAIL")) -> — | G22: SUM(E60:E64). Check E60=prior unfunded, E61=negative contribution
B23: Ending Unfunded (SI) | D23: ='Reporting Template'!G65 -> 0 | E23: =IF(C23="","",C23-D23) | F23: =IF(C23="","—",IF(ABS(C23-D23)<1,"✓ OK","✗ FAIL")) -> — | G23: G60=E59 (=total commitment). G61=negative of all SI contributions
B24: Total Commitment | D24: ='Reporting Template'!E59 -> 0 | E24: =IF(C24="","",C24-D24) | F24: =IF(C24="","—",IF(ABS(C24-D24)<1,"✓ OK","✗ FAIL")) -> — | G24: Hard input. F59/G59 are formulas =E59. Never enter F or G separately
B26: Period Continuity Checks
B27: Beginning NAV (QTD E9) = Prior Ending NAV | D27: ='Reporting Template'!E9 -> 0 | E27: =IF(C27="","",C27-D27) | F27: =IF(C27="","—",IF(ABS(C27-D27)<1,"✓ OK","✗ FAIL")) -> — | G27: E9 must equal the prior quarter E51 to the dollar
B28: YTD Mgmt Fee = Sum of All QTDs | D28: ='Reporting Template'!F14 -> 0 | E28: =IF(C28="","",C28-D28) | F28: =IF(C28="","—",IF(ABS(C28-D28)<1,"✓ OK","✗ FAIL")) -> — | G28: F14 must equal sum of all quarterly E14 values year-to-date
B29: QTD contributions = Change in committed capital | D29: ='Reporting Template'!E10 -> 0 | E29: =IF(C29="","",C29-D29) | F29: =IF(C29="","—",IF(ABS(C29-D29)<1,"✓ OK","✗ FAIL")) -> — | G29: Compare E10 to change in E65 vs prior quarter — should reconcile
B31: Sign Convention & Double-Count Rules — Reference
B32: Management fees (E14) | C32: NEGATIVE | G32: Costs to LP are negative in A.1
B33: Distributions (E11) | C33: POSITIVE | G33: Template instruction: input positive values
B34: Offsets applied (E26) | C34: POSITIVE | G34: Credits back to LP are positive in A.1
B35: B.1 Mgmt Fees (E77) | C35: POSITIVE AUTO | G35: Formula =-(E14+E15) flips sign. Never enter manually
B36: B.1 Offsets (E79) | C36: NEGATIVE AUTO | G36: Formula =-E26 flips sign. Never enter manually
B37: A.3 IA Earned (E68) | C37: POSITIVE | G37: Template: input positive even though economic cost
B38: Interest expense (E45) | C38: NEGATIVE | G38: Cost to LP. Enter as negative number
B39: Partnership sub-rows 17-25 | C39: NEGATIVE | G39: Costs. Enter negative. Row 16 is formula — do NOT enter there
B40: Offset sub-rows 28-36 | C40: POSITIVE | G40: Credits. Row 38 sums these. Row 26 is the applied total
B41: Carry periodic change (E54) | C41: VARIES | G41: Negative when carry increases. Positive when carry unwinds
B43: Colour Legend: 🟡 Orange = Input cells (enter from PDF) 🔵 Blue = Formula cells (auto-computed, never edit) 🟢 Green = Check passed 🔴 Red = Discrepancy found
